mathics3_module_nltk-9.0.2.dist-info/licenses/LICENSE
pymathics/natlang/__init__.py
pymathics/natlang/manipulate.py
pymathics/natlang/nltk.py
pymathics/natlang/normalization.py
pymathics/natlang/spacy.py
pymathics/natlang/textual_analysis.py
pymathics/natlang/util.py
pymathics/natlang/version.py
pymathics/natlang/linguistic_data/__init__.py
pymathics/natlang/linguistic_data/lang_trans.py
pymathics/natlang/linguistic_data/translation.py
mathics3_module_nltk-9.0.2.dist-info/METADATA
mathics3_module_nltk-9.0.2.dist-info/WHEEL
mathics3_module_nltk-9.0.2.dist-info/top_level.txt
mathics3_module_nltk-9.0.2.dist-info/RECORD
