Metadata-Version: 2.4
Name: Mathics3-Module-nltk
Version: 9.0.2
Summary: Mathics3 Natural Language Toolkit module
Maintainer-email: Mathics Group <mathics-devel@googlegroups.com>
License-Expression: GPL-3.0-or-later
Project-URL: Homepage, https://github.com/Mathics3/Mathics3-Module-nltk
Project-URL: Downloads, https://github.com/Mathics3/Mathics3-Module-nltk/releases
Keywords: Mathematica,Wolfram,Interpreter,Shell,Math,CAS
Classifier: Intended Audience :: Developers
Classifier: Intended Audience :: Science/Research
Classifier: Programming Language :: Python
Classifier: Programming Language :: Python :: 3.10
Classifier: Programming Language :: Python :: 3.11
Classifier: Programming Language :: Python :: 3.12
Classifier: Programming Language :: Python :: 3.13
Classifier: Programming Language :: Python :: Implementation :: CPython
Classifier: Programming Language :: Python :: Implementation :: PyPy
Classifier: Topic :: Scientific/Engineering
Classifier: Topic :: Scientific/Engineering :: Mathematics
Classifier: Topic :: Software Development :: Interpreters
Requires-Python: >=3.10
License-File: LICENSE
Requires-Dist: Mathics3>=9.0.0
Requires-Dist: Mathics3-Module-Base>=9.0.0
Requires-Dist: click>=8.0
Requires-Dist: joblib>=1.0.1
Requires-Dist: langid
Requires-Dist: llvmlite>=0.36
Requires-Dist: nltk>=3.8.0
Requires-Dist: mpmath>=1.2.0
Requires-Dist: PatternLite
Requires-Dist: pyenchant>=3.2.0
Requires-Dist: pycountry>=3.2.0
Requires-Dist: spacy>=3.4
Requires-Dist: wasabi<1.1.0,>=0.8.2
Provides-Extra: dev
Requires-Dist: pytest; extra == "dev"
Dynamic: license-file
